filemark/__init__.py
filemark/command_line.py
filemark/filemarkutils.py
filemark-0.1.2.dist-info/LICENSE
filemark-0.1.2.dist-info/METADATA
filemark-0.1.2.dist-info/WHEEL
filemark-0.1.2.dist-info/entry_points.txt
filemark-0.1.2.dist-info/top_level.txt
filemark-0.1.2.dist-info/RECORD
