Metadata-Version: 2.1
Name: filemark
Version: 0.1.2
Summary: A Python-built Command line tool for bookmarking and smartly-reopening project folders (for developers)
Home-page: https://github.com/Shreyas-Ashtamkar/File-Mark
Author: Shreyas Ashtamkar
Author-email: shreyu@programmer.net
License: MIT
Platform: UNKNOWN
Classifier: Programming Language :: Python :: 3
Classifier: Programming Language :: Python :: 3.4
Classifier: Programming Language :: Python :: 3.5
Classifier: Programming Language :: Python :: 3.6
Classifier: Programming Language :: Python :: 3.7
Classifier: Programming Language :: Python :: 3.8
Classifier: License :: OSI Approved :: MIT License
Classifier: Operating System :: POSIX :: Linux
Requires-Python: >=3.6
Requires-Dist: autopep8 (>=1.5.4)
Requires-Dist: pycodestyle (>=2.6.0)
Requires-Dist: tabulate (>=0.8.7)
Requires-Dist: toml (>=0.10.2)
